toshi_client/__init__.py
toshi_client/client.py
toshi_client/errors.py
toshi_client/index/__init__.py
toshi_client/index/enums.py
toshi_client/index/field_options.py
toshi_client/index/index.py
toshi_client/index/index_builder.py
toshi_client/index/index_summary.py
toshi_client/models/__init__.py
toshi_client/models/document.py
toshi_client/models/field_options.py
toshi_client/models/query.py
toshi_client/query/__init__.py
toshi_client/query/bool_query.py
toshi_client/query/facet_query.py
toshi_client/query/fuzzy_query.py
toshi_client/query/phrase_query.py
toshi_client/query/range_query.py
toshi_client/query/regex_query.py
toshi_client/query/term_query.py
toshi_client-0.0.1.dist-info/METADATA
toshi_client-0.0.1.dist-info/WHEEL
toshi_client-0.0.1.dist-info/licenses/LICENSE
toshi_client-0.0.1.dist-info/RECORD
