Metadata-Version: 2.3
Name: toshi_client
Version: 0.0.1
Summary: Python client for the Full-Text Search Engine Toshi
Project-URL: Homepage, https://github.com/SmartMonkey-git/py-toshi-client
Project-URL: Issues, https://github.com/SmartMonkey-git/py-toshi-client/issues
Author-email: Rouven Reuter <rouven.reuter91@gmail.com>
License-File: LICENSE
Classifier: License :: OSI Approved :: MIT License
Classifier: Operating System :: OS Independent
Classifier: Programming Language :: Python :: 3
Requires-Python: >=3.11
Requires-Dist: aiohttp>=3.9.5
Requires-Dist: requests>=2.32.3
